imagesort/__init__.py
imagesort/imagesort.py
imagesort-0.4.0.dist-info/DESCRIPTION.rst
imagesort-0.4.0.dist-info/entry_points.txt
imagesort-0.4.0.dist-info/METADATA
imagesort-0.4.0.dist-info/metadata.json
imagesort-0.4.0.dist-info/RECORD
imagesort-0.4.0.dist-info/top_level.txt
imagesort-0.4.0.dist-info/WHEEL
