Metadata-Version: 2.0
Name: imagesort
Version: 0.4.0
Summary: Organize image files by date taken
Home-page: https://github.com/leinz/imagesort
Author: Børge Lanes
Author-email: borge.lanes@gmail.com
License: MIT
Keywords: media
Platform: UNKNOWN
Classifier: Development Status :: 4 - Beta
Classifier: License :: OSI Approved :: MIT License
Classifier: Operating System :: OS Independent
Classifier: Topic :: Multimedia
Classifier: Programming Language :: Python :: 2.7
Classifier: Programming Language :: Python :: 3
Requires-Dist: ExifRead (>=2.1)
